Workbook

Sheet Start
B2: Earned value calculator | E2: The Project Control Hub
B3: Three numbers a month in; where the job ends, what recovery would take, and how late it is, out.
B4: The Project Control Hub · free template
B7: EVERY MONTH, IN FIVE STEPS
B8: 1 | C8: Setup → | D8: Once: BAC, duration, the date month 1 ends. Every month: change "This report: month". | E8: 1 minute
B9: 2 | C9: Monthly → | D9: Once: the baseline PV, month by month. Every month: EV and AC for the new row. | E9: 5 minutes
B10: 3 | C10: Work packages → | D10: EV and AC by package, each measured by a rule agreed in advance. The totals check against Monthly. | E10: 20 minutes
B11: 4 | C11: Results → | D11: Read it. Every measure, with one line on what it means, and four ways to forecast the finish. | E11: 5 minutes
B12: 5 | C12: Dashboard → | D12: Take it to the meeting. Say the plain-English paragraph out loud. | E12: —
B14: THE THREE NUMBERS
C15: PV · the promise | D15: What the baseline said would be built by now. Comes from the schedule, once.
C16: EV · what is standing | D16: The budget of the work actually done, measured. Never "about eighty percent".
C17: AC · what was paid | D17: What has left the bank. Ask accounts.
C18: EV against AC tells you about cost. EV against PV tells you about time. PV against AC tells you nothing.
B20: HOW TO READ THE CELLS
C21: Yellow, blue text | D21: Yours to fill in.
C22: White, black text | D22: A formula. Leave it alone and it keeps working.
C23: Teal row | D23: The reporting month.
C24: Amber | D24: An index between 0.90 and 1.00: watch it.
C25: Red | D25: An index under 0.90, a negative variance, or a TCPI the site has never achieved.
B27: WHAT IS IN THIS FILE
C28: Dashboard | D28: Six numbers, a paragraph in plain English, four charts and the work packages.
C29: Setup | D29: BAC, duration, the reporting month.
C30: Monthly | D30: PV, EV and AC month by month, with CPI, SPI, earned schedule and the forecast curve.
C31: Results | D31: Every measure for the month, explained, and four EAC methods side by side.
C32: Work packages | D32: EV and AC by package, so you can see where the money goes.
B34: EXPLAINED IN
C35: Schedule Topic 18 · EVM fundamentals
C36: Schedule Topic 19 · EVM analysis
C37: Schedule Topic 20 · Forecasting
C38: Cost & Cash Topic 6 · Why CPI flatters a tender sum
B40: Blank: twenty-four months and twenty work packages ready to fill. The example file shows month six of the example project.
B44: Free to use and adapt on your own projects. https://theprojectcontrolhub.com/

Sheet Dashboard
B2: Earned value | K2: The Project Control Hub
B3: =IF(OR(Setup!B6="",Setup!B9=""),"Fill in the Setup sheet first",Setup!B6&" · month "&Setup!B9&" of "&Setup!B8&IF(Setup!B10="",""," · "&TEXT(EOMONTH(Setup!B10,Setup!B9-1),"mmm yyyy"))&" · BAC "&TEXT(Setup!B7,"$#,##0"))
B5: CPI · COST | D5: SPI(t) · TIME | F5: ESTIMATE AT COMPLETION | H5: OVERRUN AT COMPLETION | J5: TCPI · NEEDED FROM NOW | L5: STILL TO PAY OUT | P5: Chart data
B6: =Results!B9 | D6: =Results!B25 | F6: =Results!B15 | H6: =Results!B16 | J6: =Results!B18 | L6: =Results!B17 | P6: CPI achieved | Q6: =Results!B9
P7: Best month | Q7: =Results!B20
B8: =IF(Results!B9="","",TEXT(Results!B9*100,"0")&" cents of work per dollar") | D8: =IF(Results!B26="","",TEXT(Results!B26,"0.0")&" month(s) behind · SPI $ "&TEXT(Results!B10,"0.00")) | F8: =IF(Results!B14="","","budget "&TEXT(Results!B14/1000,"$#,##0")&"k") | H8: ="BAC minus EAC" | J8: =IF(Results!B19="","",TEXT(Results!B19,"+0%")&" on the proven rate · best month "&TEXT(Results!B20,"0.00")) | L8: ="estimate to complete" | P8: TCPI needed | Q8: =Results!B18
B11: =Results!A41
B13: =Results!B21
B15: THE THREE NUMBERS, AND WHERE THEY LEAD
B33: WHERE THE MONEY IS LOST, AND WHAT RECOVERY WOULD TAKE
B52: WORK PACKAGES
B53: Package | E53: Budget | F53: PV | G53: EV | H53: AC | I53: CV | J53: CPI | K53: SPI | L53: Flag
B54: =IF('Work packages'!$A$7="","",'Work packages'!A7) | E54: =IF('Work packages'!$A$7="","",'Work packages'!B7) | F54: =IF('Work packages'!$A$7="","",'Work packages'!F7) | G54: =IF('Work packages'!$A$7="","",'Work packages'!G7) | H54: =IF('Work packages'!$A$7="","",'Work packages'!H7) | I54: =IF('Work packages'!$A$7="","",'Work packages'!I7) | J54: =IF('Work packages'!$A$7="","",'Work packages'!K7) | K54: =IF('Work packages'!$A$7="","",'Work packages'!L7) | L54: =IF('Work packages'!$A$7="","",'Work packages'!M7)
B55: =IF('Work packages'!$A$8="","",'Work packages'!A8) | E55: =IF('Work packages'!$A$8="","",'Work packages'!B8) | F55: =IF('Work packages'!$A$8="","",'Work packages'!F8) | G55: =IF('Work packages'!$A$8="","",'Work packages'!G8) | H55: =IF('Work packages'!$A$8="","",'Work packages'!H8) | I55: =IF('Work packages'!$A$8="","",'Work packages'!I8) | J55: =IF('Work packages'!$A$8="","",'Work packages'!K8) | K55: =IF('Work packages'!$A$8="","",'Work packages'!L8) | L55: =IF('Work packages'!$A$8="","",'Work packages'!M8)
B56: =IF('Work packages'!$A$9="","",'Work packages'!A9) | E56: =IF('Work packages'!$A$9="","",'Work packages'!B9) | F56: =IF('Work packages'!$A$9="","",'Work packages'!F9) | G56: =IF('Work packages'!$A$9="","",'Work packages'!G9) | H56: =IF('Work packages'!$A$9="","",'Work packages'!H9) | I56: =IF('Work packages'!$A$9="","",'Work packages'!I9) | J56: =IF('Work packages'!$A$9="","",'Work packages'!K9) | K56: =IF('Work packages'!$A$9="","",'Work packages'!L9) | L56: =IF('Work packages'!$A$9="","",'Work packages'!M9)
B57: =IF('Work packages'!$A$10="","",'Work packages'!A10) | E57: =IF('Work packages'!$A$10="","",'Work packages'!B10) | F57: =IF('Work packages'!$A$10="","",'Work packages'!F10) | G57: =IF('Work packages'!$A$10="","",'Work packages'!G10) | H57: =IF('Work packages'!$A$10="","",'Work packages'!H10) | I57: =IF('Work packages'!$A$10="","",'Work packages'!I10) | J57: =IF('Work packages'!$A$10="","",'Work packages'!K10) | K57: =IF('Work packages'!$A$10="","",'Work packages'!L10) | L57: =IF('Work packages'!$A$10="","",'Work packages'!M10)
B58: =IF('Work packages'!$A$11="","",'Work packages'!A11) | E58: =IF('Work packages'!$A$11="","",'Work packages'!B11) | F58: =IF('Work packages'!$A$11="","",'Work packages'!F11) | G58: =IF('Work packages'!$A$11="","",'Work packages'!G11) | H58: =IF('Work packages'!$A$11="","",'Work packages'!H11) | I58: =IF('Work packages'!$A$11="","",'Work packages'!I11) | J58: =IF('Work packages'!$A$11="","",'Work packages'!K11) | K58: =IF('Work packages'!$A$11="","",'Work packages'!L11) | L58: =IF('Work packages'!$A$11="","",'Work packages'!M11)
B59: =IF('Work packages'!$A$12="","",'Work packages'!A12) | E59: =IF('Work packages'!$A$12="","",'Work packages'!B12) | F59: =IF('Work packages'!$A$12="","",'Work packages'!F12) | G59: =IF('Work packages'!$A$12="","",'Work packages'!G12) | H59: =IF('Work packages'!$A$12="","",'Work packages'!H12) | I59: =IF('Work packages'!$A$12="","",'Work packages'!I12) | J59: =IF('Work packages'!$A$12="","",'Work packages'!K12) | K59: =IF('Work packages'!$A$12="","",'Work packages'!L12) | L59: =IF('Work packages'!$A$12="","",'Work packages'!M12)
B60: =IF('Work packages'!$A$13="","",'Work packages'!A13) | E60: =IF('Work packages'!$A$13="","",'Work packages'!B13) | F60: =IF('Work packages'!$A$13="","",'Work packages'!F13) | G60: =IF('Work packages'!$A$13="","",'Work packages'!G13) | H60: =IF('Work packages'!$A$13="","",'Work packages'!H13) | I60: =IF('Work packages'!$A$13="","",'Work packages'!I13) | J60: =IF('Work packages'!$A$13="","",'Work packages'!K13) | K60: =IF('Work packages'!$A$13="","",'Work packages'!L13) | L60: =IF('Work packages'!$A$13="","",'Work packages'!M13)
B61: =IF('Work packages'!$A$14="","",'Work packages'!A14) | E61: =IF('Work packages'!$A$14="","",'Work packages'!B14) | F61: =IF('Work packages'!$A$14="","",'Work packages'!F14) | G61: =IF('Work packages'!$A$14="","",'Work packages'!G14) | H61: =IF('Work packages'!$A$14="","",'Work packages'!H14) | I61: =IF('Work packages'!$A$14="","",'Work packages'!I14) | J61: =IF('Work packages'!$A$14="","",'Work packages'!K14) | K61: =IF('Work packages'!$A$14="","",'Work packages'!L14) | L61: =IF('Work packages'!$A$14="","",'Work packages'!M14)
B62: =IF('Work packages'!$A$15="","",'Work packages'!A15) | E62: =IF('Work packages'!$A$15="","",'Work packages'!B15) | F62: =IF('Work packages'!$A$15="","",'Work packages'!F15) | G62: =IF('Work packages'!$A$15="","",'Work packages'!G15) | H62: =IF('Work packages'!$A$15="","",'Work packages'!H15) | I62: =IF('Work packages'!$A$15="","",'Work packages'!I15) | J62: =IF('Work packages'!$A$15="","",'Work packages'!K15) | K62: =IF('Work packages'!$A$15="","",'Work packages'!L15) | L62: =IF('Work packages'!$A$15="","",'Work packages'!M15)
B63: =IF('Work packages'!$A$16="","",'Work packages'!A16) | E63: =IF('Work packages'!$A$16="","",'Work packages'!B16) | F63: =IF('Work packages'!$A$16="","",'Work packages'!F16) | G63: =IF('Work packages'!$A$16="","",'Work packages'!G16) | H63: =IF('Work packages'!$A$16="","",'Work packages'!H16) | I63: =IF('Work packages'!$A$16="","",'Work packages'!I16) | J63: =IF('Work packages'!$A$16="","",'Work packages'!K16) | K63: =IF('Work packages'!$A$16="","",'Work packages'!L16) | L63: =IF('Work packages'!$A$16="","",'Work packages'!M16)
B65: Everything on this page reads from Monthly, Results and Work packages.

Sheet Setup
A1: Setup | D1: The Project Control Hub
A2: The budget, the duration and the month you are reporting.
A3: Change "This report: month" every month. Everything else reads from here.
A6: Project
A7: Budget at completion, BAC ($) | D7: The budget you control. A tender sum carries overhead, profit and reserve: dividing invoices by it flatters CPI (Cost & Cash Topics 5 and 6).
A8: Planned duration (months)
A9: This report: month | D9: The row of the Monthly sheet the Dashboard and Results read.
A10: Month 1 ends on | D10: Optional. Dates the Monthly rows and the forecast finish.
A11: Prepared by

Sheet Monthly
A1: Monthly | N1: The Project Control Hub
A2: The three numbers every month: the promise (PV), what is standing (EV), what has been paid (AC).
A3: PV comes from the baseline once. Each month add EV (measured, never "about eighty percent") and AC (ask accounts).
A6: Month | B6: Month end | C6: Planned value, PV (cumulative $) | D6: Earned value, EV (cumulative $) | E6: Actual cost, AC (cumulative $) | F6: Cost variance, CV ($) | G6: Schedule variance, SV ($) | H6: CPI | I6: SPI ($) | J6: Earned schedule (months) | K6: SPI(t) | L6: Delay (months) | M6: CPI this month | N6: Forecast cost if nothing changes ($) | O6: Target 1.0 | P6: CPI | Q6: SPI(t) | R6: Forecast cost if nothing changes
A7: 1 | B7: =IF(Setup!$B$10="","",EOMONTH(Setup!$B$10,A7-1)) | F7: =IF(OR(D7="",E7=""),"",D7-E7) | G7: =IF(OR(D7="",C7=""),"",D7-C7) | H7: =IF(OR(D7="",E7="",E7=0),"",D7/E7) | I7: =IF(OR(D7="",C7="",C7=0),"",D7/C7) | J7: =IF(OR(D7="",COUNT($C$7:$C$30)=0),"",IF(COUNTIF($C$7:$C$30,"<="&D7)=0,D7/$C$7,IF(COUNTIF($C$7:$C$30,"<="&D7)>=COUNT($C$7:$C$30),COUNTIF($C$7:$C$30,"<="&D7),COUNTIF($C$7:$C$30,"<="&D7)+(D7-INDEX($C$7:$C$30,COUNTIF($C$7:$C$30,"<="&D7)))/(INDEX($C$7:$C$30,COUNTIF($C$7:$C$30,"<="&D7)+1)-INDEX($C$7:$C$30,COUNTIF($C$7:$C$30,"<="&D7)))))) | K7: =IF(J7="","",J7/A7) | L7: =IF(J7="","",A7-J7) | M7: =IF(OR(D7="",E7="",(E7)=0),"",(D7)/(E7)) | N7: =IF(OR(Setup!$B$9="",A7<Setup!$B$9),"",IF(A7=Setup!$B$9,E7,IF(OR(C7="",Results!$B$9="",Results!$B$9=0),"",Results!$B$8+MAX(0,C7-Results!$B$7)/Results!$B$9))) | O7: =IF(D7="",NA(),1) | P7: =IF(H7="",NA(),H7) | Q7: =IF(K7="",NA(),K7) | R7: =IF(N7="",NA(),N7)
A8: 2 | B8: =IF(Setup!$B$10="","",EOMONTH(Setup!$B$10,A8-1)) | F8: =IF(OR(D8="",E8=""),"",D8-E8) | G8: =IF(OR(D8="",C8=""),"",D8-C8) | H8: =IF(OR(D8="",E8="",E8=0),"",D8/E8) | I8: =IF(OR(D8="",C8="",C8=0),"",D8/C8) | J8: =IF(OR(D8="",COUNT($C$7:$C$30)=0),"",IF(COUNTIF($C$7:$C$30,"<="&D8)=0,D8/$C$7,IF(COUNTIF($C$7:$C$30,"<="&D8)>=COUNT($C$7:$C$30),COUNTIF($C$7:$C$30,"<="&D8),COUNTIF($C$7:$C$30,"<="&D8)+(D8-INDEX($C$7:$C$30,COUNTIF($C$7:$C$30,"<="&D8)))/(INDEX($C$7:$C$30,COUNTIF($C$7:$C$30,"<="&D8)+1)-INDEX($C$7:$C$30,COUNTIF($C$7:$C$30,"<="&D8)))))) | K8: =IF(J8="","",J8/A8) | L8: =IF(J8="","",A8-J8) | M8: =IF(OR(D8="",E8="",(E8-E7)=0),"",(D8-D7)/(E8-E7)) | N8: =IF(OR(Setup!$B$9="",A8<Setup!$B$9),"",IF(A8=Setup!$B$9,E8,IF(OR(C8="",Results!$B$9="",Results!$B$9=0),"",Results!$B$8+MAX(0,C8-Results!$B$7)/Results!$B$9))) | O8: =IF(D8="",NA(),1) | P8: =IF(H8="",NA(),H8) | Q8: =IF(K8="",NA(),K8) | R8: =IF(N8="",NA(),N8)
A9: 3 | B9: =IF(Setup!$B$10="","",EOMONTH(Setup!$B$10,A9-1)) | F9: =IF(OR(D9="",E9=""),"",D9-E9) | G9: =IF(OR(D9="",C9=""),"",D9-C9) | H9: =IF(OR(D9="",E9="",E9=0),"",D9/E9) | I9: =IF(OR(D9="",C9="",C9=0),"",D9/C9) | J9: =IF(OR(D9="",COUNT($C$7:$C$30)=0),"",IF(COUNTIF($C$7:$C$30,"<="&D9)=0,D9/$C$7,IF(COUNTIF($C$7:$C$30,"<="&D9)>=COUNT($C$7:$C$30),COUNTIF($C$7:$C$30,"<="&D9),COUNTIF($C$7:$C$30,"<="&D9)+(D9-INDEX($C$7:$C$30,COUNTIF($C$7:$C$30,"<="&D9)))/(INDEX($C$7:$C$30,COUNTIF($C$7:$C$30,"<="&D9)+1)-INDEX($C$7:$C$30,COUNTIF($C$7:$C$30,"<="&D9)))))) | K9: =IF(J9="","",J9/A9) | L9: =IF(J9="","",A9-J9) | M9: =IF(OR(D9="",E9="",(E9-E8)=0),"",(D9-D8)/(E9-E8)) | N9: =IF(OR(Setup!$B$9="",A9<Setup!$B$9),"",IF(A9=Setup!$B$9,E9,IF(OR(C9="",Results!$B$9="",Results!$B$9=0),"",Results!$B$8+MAX(0,C9-Results!$B$7)/Results!$B$9))) | O9: =IF(D9="",NA(),1) | P9: =IF(H9="",NA(),H9) | Q9: =IF(K9="",NA(),K9) | R9: =IF(N9="",NA(),N9)
A10: 4 | B10: =IF(Setup!$B$10="","",EOMONTH(Setup!$B$10,A10-1)) | F10: =IF(OR(D10="",E10=""),"",D10-E10) | G10: =IF(OR(D10="",C10=""),"",D10-C10) | H10: =IF(OR(D10="",E10="",E10=0),"",D10/E10) | I10: =IF(OR(D10="",C10="",C10=0),"",D10/C10) | J10: =IF(OR(D10="",COUNT($C$7:$C$30)=0),"",IF(COUNTIF($C$7:$C$30,"<="&D10)=0,D10/$C$7,IF(COUNTIF($C$7:$C$30,"<="&D10)>=COUNT($C$7:$C$30),COUNTIF($C$7:$C$30,"<="&D10),COUNTIF($C$7:$C$30,"<="&D10)+(D10-INDEX($C$7:$C$30,COUNTIF($C$7:$C$30,"<="&D10)))/(INDEX($C$7:$C$30,COUNTIF($C$7:$C$30,"<="&D10)+1)-INDEX($C$7:$C$30,COUNTIF($C$7:$C$30,"<="&D10)))))) | K10: =IF(J10="","",J10/A10) | L10: =IF(J10="","",A10-J10) | M10: =IF(OR(D10="",E10="",(E10-E9)=0),"",(D10-D9)/(E10-E9)) | N10: =IF(OR(Setup!$B$9="",A10<Setup!$B$9),"",IF(A10=Setup!$B$9,E10,IF(OR(C10="",Results!$B$9="",Results!$B$9=0),"",Results!$B$8+MAX(0,C10-Results!$B$7)/Results!$B$9))) | O10: =IF(D10="",NA(),1) | P10: =IF(H10="",NA(),H10) | Q10: =IF(K10="",NA(),K10) | R10: =IF(N10="",NA(),N10)
A11: 5 | B11: =IF(Setup!$B$10="","",EOMONTH(Setup!$B$10,A11-1)) | F11: =IF(OR(D11="",E11=""),"",D11-E11) | G11: =IF(OR(D11="",C11=""),"",D11-C11) | H11: =IF(OR(D11="",E11="",E11=0),"",D11/E11) | I11: =IF(OR(D11="",C11="",C11=0),"",D11/C11) | J11: =IF(OR(D11="",COUNT($C$7:$C$30)=0),"",IF(COUNTIF($C$7:$C$30,"<="&D11)=0,D11/$C$7,IF(COUNTIF($C$7:$C$30,"<="&D11)>=COUNT($C$7:$C$30),COUNTIF($C$7:$C$30,"<="&D11),COUNTIF($C$7:$C$30,"<="&D11)+(D11-INDEX($C$7:$C$30,COUNTIF($C$7:$C$30,"<="&D11)))/(INDEX($C$7:$C$30,COUNTIF($C$7:$C$30,"<="&D11)+1)-INDEX($C$7:$C$30,COUNTIF($C$7:$C$30,"<="&D11)))))) | K11: =IF(J11="","",J11/A11) | L11: =IF(J11="","",A11-J11) | M11: =IF(OR(D11="",E11="",(E11-E10)=0),"",(D11-D10)/(E11-E10)) | N11: =IF(OR(Setup!$B$9="",A11<Setup!$B$9),"",IF(A11=Setup!$B$9,E11,IF(OR(C11="",Results!$B$9="",Results!$B$9=0),"",Results!$B$8+MAX(0,C11-Results!$B$7)/Results!$B$9))) | O11: =IF(D11="",NA(),1) | P11: =IF(H11="",NA(),H11) | Q11: =IF(K11="",NA(),K11) | R11: =IF(N11="",NA(),N11)
A12: 6 | B12: =IF(Setup!$B$10="","",EOMONTH(Setup!$B$10,A12-1)) | F12: =IF(OR(D12="",E12=""),"",D12-E12) | G12: =IF(OR(D12="",C12=""),"",D12-C12) | H12: =IF(OR(D12="",E12="",E12=0),"",D12/E12) | I12: =IF(OR(D12="",C12="",C12=0),"",D12/C12) | J12: =IF(OR(D12="",COUNT($C$7:$C$30)=0),"",IF(COUNTIF($C$7:$C$30,"<="&D12)=0,D12/$C$7,IF(COUNTIF($C$7:$C$30,"<="&D12)>=COUNT($C$7:$C$30),COUNTIF($C$7:$C$30,"<="&D12),COUNTIF($C$7:$C$30,"<="&D12)+(D12-INDEX($C$7:$C$30,COUNTIF($C$7:$C$30,"<="&D12)))/(INDEX($C$7:$C$30,COUNTIF($C$7:$C$30,"<="&D12)+1)-INDEX($C$7:$C$30,COUNTIF($C$7:$C$30,"<="&D12)))))) | K12: =IF(J12="","",J12/A12) | L12: =IF(J12="","",A12-J12) | M12: =IF(OR(D12="",E12="",(E12-E11)=0),"",(D12-D11)/(E12-E11)) | N12: =IF(OR(Setup!$B$9="",A12<Setup!$B$9),"",IF(A12=Setup!$B$9,E12,IF(OR(C12="",Results!$B$9="",Results!$B$9=0),"",Results!$B$8+MAX(0,C12-Results!$B$7)/Results!$B$9))) | O12: =IF(D12="",NA(),1) | P12: =IF(H12="",NA(),H12) | Q12: =IF(K12="",NA(),K12) | R12: =IF(N12="",NA(),N12)
A13: 7 | B13: =IF(Setup!$B$10="","",EOMONTH(Setup!$B$10,A13-1)) | F13: =IF(OR(D13="",E13=""),"",D13-E13) | G13: =IF(OR(D13="",C13=""),"",D13-C13) | H13: =IF(OR(D13="",E13="",E13=0),"",D13/E13) | I13: =IF(OR(D13="",C13="",C13=0),"",D13/C13) | J13: =IF(OR(D13="",COUNT($C$7:$C$30)=0),"",IF(COUNTIF($C$7:$C$30,"<="&D13)=0,D13/$C$7,IF(COUNTIF($C$7:$C$30,"<="&D13)>=COUNT($C$7:$C$30),COUNTIF($C$7:$C$30,"<="&D13),COUNTIF($C$7:$C$30,"<="&D13)+(D13-INDEX($C$7:$C$30,COUNTIF($C$7:$C$30,"<="&D13)))/(INDEX($C$7:$C$30,COUNTIF($C$7:$C$30,"<="&D13)+1)-INDEX($C$7:$C$30,COUNTIF($C$7:$C$30,"<="&D13)))))) | K13: =IF(J13="","",J13/A13) | L13: =IF(J13="","",A13-J13) | M13: =IF(OR(D13="",E13="",(E13-E12)=0),"",(D13-D12)/(E13-E12)) | N13: =IF(OR(Setup!$B$9="",A13<Setup!$B$9),"",IF(A13=Setup!$B$9,E13,IF(OR(C13="",Results!$B$9="",Results!$B$9=0),"",Results!$B$8+MAX(0,C13-Results!$B$7)/Results!$B$9))) | O13: =IF(D13="",NA(),1) | P13: =IF(H13="",NA(),H13) | Q13: =IF(K13="",NA(),K13) | R13: =IF(N13="",NA(),N13)
A14: 8 | B14: =IF(Setup!$B$10="","",EOMONTH(Setup!$B$10,A14-1)) | F14: =IF(OR(D14="",E14=""),"",D14-E14) | G14: =IF(OR(D14="",C14=""),"",D14-C14) | H14: =IF(OR(D14="",E14="",E14=0),"",D14/E14) | I14: =IF(OR(D14="",C14="",C14=0),"",D14/C14) | J14: =IF(OR(D14="",COUNT($C$7:$C$30)=0),"",IF(COUNTIF($C$7:$C$30,"<="&D14)=0,D14/$C$7,IF(COUNTIF($C$7:$C$30,"<="&D14)>=COUNT($C$7:$C$30),COUNTIF($C$7:$C$30,"<="&D14),COUNTIF($C$7:$C$30,"<="&D14)+(D14-INDEX($C$7:$C$30,COUNTIF($C$7:$C$30,"<="&D14)))/(INDEX($C$7:$C$30,COUNTIF($C$7:$C$30,"<="&D14)+1)-INDEX($C$7:$C$30,COUNTIF($C$7:$C$30,"<="&D14)))))) | K14: =IF(J14="","",J14/A14) | L14: =IF(J14="","",A14-J14) | M14: =IF(OR(D14="",E14="",(E14-E13)=0),"",(D14-D13)/(E14-E13)) | N14: =IF(OR(Setup!$B$9="",A14<Setup!$B$9),"",IF(A14=Setup!$B$9,E14,IF(OR(C14="",Results!$B$9="",Results!$B$9=0),"",Results!$B$8+MAX(0,C14-Results!$B$7)/Results!$B$9))) | O14: =IF(D14="",NA(),1) | P14: =IF(H14="",NA(),H14) | Q14: =IF(K14="",NA(),K14) | R14: =IF(N14="",NA(),N14)
A15: 9 | B15: =IF(Setup!$B$10="","",EOMONTH(Setup!$B$10,A15-1)) | F15: =IF(OR(D15="",E15=""),"",D15-E15) | G15: =IF(OR(D15="",C15=""),"",D15-C15) | H15: =IF(OR(D15="",E15="",E15=0),"",D15/E15) | I15: =IF(OR(D15="",C15="",C15=0),"",D15/C15) | J15: =IF(OR(D15="",COUNT($C$7:$C$30)=0),"",IF(COUNTIF($C$7:$C$30,"<="&D15)=0,D15/$C$7,IF(COUNTIF($C$7:$C$30,"<="&D15)>=COUNT($C$7:$C$30),COUNTIF($C$7:$C$30,"<="&D15),COUNTIF($C$7:$C$30,"<="&D15)+(D15-INDEX($C$7:$C$30,COUNTIF($C$7:$C$30,"<="&D15)))/(INDEX($C$7:$C$30,COUNTIF($C$7:$C$30,"<="&D15)+1)-INDEX($C$7:$C$30,COUNTIF($C$7:$C$30,"<="&D15)))))) | K15: =IF(J15="","",J15/A15) | L15: =IF(J15="","",A15-J15) | M15: =IF(OR(D15="",E15="",(E15-E14)=0),"",(D15-D14)/(E15-E14)) | N15: =IF(OR(Setup!$B$9="",A15<Setup!$B$9),"",IF(A15=Setup!$B$9,E15,IF(OR(C15="",Results!$B$9="",Results!$B$9=0),"",Results!$B$8+MAX(0,C15-Results!$B$7)/Results!$B$9))) | O15: =IF(D15="",NA(),1) | P15: =IF(H15="",NA(),H15) | Q15: =IF(K15="",NA(),K15) | R15: =IF(N15="",NA(),N15)
A16: 10 | B16: =IF(Setup!$B$10="","",EOMONTH(Setup!$B$10,A16-1)) | F16: =IF(OR(D16="",E16=""),"",D16-E16) | G16: =IF(OR(D16="",C16=""),"",D16-C16) | H16: =IF(OR(D16="",E16="",E16=0),"",D16/E16) | I16: =IF(OR(D16="",C16="",C16=0),"",D16/C16) | J16: =IF(OR(D16="",COUNT($C$7:$C$30)=0),"",IF(COUNTIF($C$7:$C$30,"<="&D16)=0,D16/$C$7,IF(COUNTIF($C$7:$C$30,"<="&D16)>=COUNT($C$7:$C$30),COUNTIF($C$7:$C$30,"<="&D16),COUNTIF($C$7:$C$30,"<="&D16)+(D16-INDEX($C$7:$C$30,COUNTIF($C$7:$C$30,"<="&D16)))/(INDEX($C$7:$C$30,COUNTIF($C$7:$C$30,"<="&D16)+1)-INDEX($C$7:$C$30,COUNTIF($C$7:$C$30,"<="&D16)))))) | K16: =IF(J16="","",J16/A16) | L16: =IF(J16="","",A16-J16) | M16: =IF(OR(D16="",E16="",(E16-E15)=0),"",(D16-D15)/(E16-E15)) | N16: =IF(OR(Setup!$B$9="",A16<Setup!$B$9),"",IF(A16=Setup!$B$9,E16,IF(OR(C16="",Results!$B$9="",Results!$B$9=0),"",Results!$B$8+MAX(0,C16-Results!$B$7)/Results!$B$9))) | O16: =IF(D16="",NA(),1) | P16: =IF(H16="",NA(),H16) | Q16: =IF(K16="",NA(),K16) | R16: =IF(N16="",NA(),N16)
A17: 11 | B17: =IF(Setup!$B$10="","",EOMONTH(Setup!$B$10,A17-1)) | F17: =IF(OR(D17="",E17=""),"",D17-E17) | G17: =IF(OR(D17="",C17=""),"",D17-C17) | H17: =IF(OR(D17="",E17="",E17=0),"",D17/E17) | I17: =IF(OR(D17="",C17="",C17=0),"",D17/C17) | J17: =IF(OR(D17="",COUNT($C$7:$C$30)=0),"",IF(COUNTIF($C$7:$C$30,"<="&D17)=0,D17/$C$7,IF(COUNTIF($C$7:$C$30,"<="&D17)>=COUNT($C$7:$C$30),COUNTIF($C$7:$C$30,"<="&D17),COUNTIF($C$7:$C$30,"<="&D17)+(D17-INDEX($C$7:$C$30,COUNTIF($C$7:$C$30,"<="&D17)))/(INDEX($C$7:$C$30,COUNTIF($C$7:$C$30,"<="&D17)+1)-INDEX($C$7:$C$30,COUNTIF($C$7:$C$30,"<="&D17)))))) | K17: =IF(J17="","",J17/A17) | L17: =IF(J17="","",A17-J17) | M17: =IF(OR(D17="",E17="",(E17-E16)=0),"",(D17-D16)/(E17-E16)) | N17: =IF(OR(Setup!$B$9="",A17<Setup!$B$9),"",IF(A17=Setup!$B$9,E17,IF(OR(C17="",Results!$B$9="",Results!$B$9=0),"",Results!$B$8+MAX(0,C17-Results!$B$7)/Results!$B$9))) | O17: =IF(D17="",NA(),1) | P17: =IF(H17="",NA(),H17) | Q17: =IF(K17="",NA(),K17) | R17: =IF(N17="",NA(),N17)
A18: 12 | B18: =IF(Setup!$B$10="","",EOMONTH(Setup!$B$10,A18-1)) | F18: =IF(OR(D18="",E18=""),"",D18-E18) | G18: =IF(OR(D18="",C18=""),"",D18-C18) | H18: =IF(OR(D18="",E18="",E18=0),"",D18/E18) | I18: =IF(OR(D18="",C18="",C18=0),"",D18/C18) | J18: =IF(OR(D18="",COUNT($C$7:$C$30)=0),"",IF(COUNTIF($C$7:$C$30,"<="&D18)=0,D18/$C$7,IF(COUNTIF($C$7:$C$30,"<="&D18)>=COUNT($C$7:$C$30),COUNTIF($C$7:$C$30,"<="&D18),COUNTIF($C$7:$C$30,"<="&D18)+(D18-INDEX($C$7:$C$30,COUNTIF($C$7:$C$30,"<="&D18)))/(INDEX($C$7:$C$30,COUNTIF($C$7:$C$30,"<="&D18)+1)-INDEX($C$7:$C$30,COUNTIF($C$7:$C$30,"<="&D18)))))) | K18: =IF(J18="","",J18/A18) | L18: =IF(J18="","",A18-J18) | M18: =IF(OR(D18="",E18="",(E18-E17)=0),"",(D18-D17)/(E18-E17)) | N18: =IF(OR(Setup!$B$9="",A18<Setup!$B$9),"",IF(A18=Setup!$B$9,E18,IF(OR(C18="",Results!$B$9="",Results!$B$9=0),"",Results!$B$8+MAX(0,C18-Results!$B$7)/Results!$B$9))) | O18: =IF(D18="",NA(),1) | P18: =IF(H18="",NA(),H18) | Q18: =IF(K18="",NA(),K18) | R18: =IF(N18="",NA(),N18)
A19: 13 | B19: =IF(Setup!$B$10="","",EOMONTH(Setup!$B$10,A19-1)) | F19: =IF(OR(D19="",E19=""),"",D19-E19) | G19: =IF(OR(D19="",C19=""),"",D19-C19) | H19: =IF(OR(D19="",E19="",E19=0),"",D19/E19) | I19: =IF(OR(D19="",C19="",C19=0),"",D19/C19) | J19: =IF(OR(D19="",COUNT($C$7:$C$30)=0),"",IF(COUNTIF($C$7:$C$30,"<="&D19)=0,D19/$C$7,IF(COUNTIF($C$7:$C$30,"<="&D19)>=COUNT($C$7:$C$30),COUNTIF($C$7:$C$30,"<="&D19),COUNTIF($C$7:$C$30,"<="&D19)+(D19-INDEX($C$7:$C$30,COUNTIF($C$7:$C$30,"<="&D19)))/(INDEX($C$7:$C$30,COUNTIF($C$7:$C$30,"<="&D19)+1)-INDEX($C$7:$C$30,COUNTIF($C$7:$C$30,"<="&D19)))))) | K19: =IF(J19="","",J19/A19) | L19: =IF(J19="","",A19-J19) | M19: =IF(OR(D19="",E19="",(E19-E18)=0),"",(D19-D18)/(E19-E18)) | N19: =IF(OR(Setup!$B$9="",A19<Setup!$B$9),"",IF(A19=Setup!$B$9,E19,IF(OR(C19="",Results!$B$9="",Results!$B$9=0),"",Results!$B$8+MAX(0,C19-Results!$B$7)/Results!$B$9))) | O19: =IF(D19="",NA(),1) | P19: =IF(H19="",NA(),H19) | Q19: =IF(K19="",NA(),K19) | R19: =IF(N19="",NA(),N19)
... A30: 24 | B30: =IF(Setup!$B$10="","",EOMONTH(Setup!$B$10,A30-1)) | F30: =IF(OR(D30="",E30=""),"",D30-E30) | G30: =IF(OR(D30="",C30=""),"",D30-C30) | H30: =IF(OR(D30="",E30="",E30=0),"",D30/E30) | I30: =IF(OR(D30="",C30="",C30=0),"",D30/C30) | J30: =IF(OR(D30="",COUNT($C$7:$C$30)=0),"",IF(COUNTIF($C$7:$C$30,"<="&D30)=0,D30/$C$7,IF(COUNTIF($C$7:$C$30,"<="&D30)>=COUNT($C$7:$C$30),COUNTIF($C$7:$C$30,"<="&D30),COUNTIF($C$7:$C$30,"<="&D30)+(D30-INDEX($C$7:$C$30,COUNTIF($C$7:$C$30,"<="&D30)))/(INDEX($C$7:$C$30,COUNTIF($C$7:$C$30,"<="&D30)+1)-INDEX($C$7:$C$30,COUNTIF($C$7:$C$30,"<="&D30)))))) | K30: =IF(J30="","",J30/A30) | L30: =IF(J30="","",A30-J30) | M30: =IF(OR(D30="",E30="",(E30-E29)=0),"",(D30-D29)/(E30-E29)) | N30: =IF(OR(Setup!$B$9="",A30<Setup!$B$9),"",IF(A30=Setup!$B$9,E30,IF(OR(C30="",Results!$B$9="",Results!$B$9=0),"",Results!$B$8+MAX(0,C30-Results!$B$7)/Results!$B$9))) | O30: =IF(D30="",NA(),1) | P30: =IF(H30="",NA(),H30) | Q30: =IF(K30="",NA(),K30) | R30: =IF(N30="",NA(),N30)
A32: Earned schedule: the month the baseline said you would reach today’s EV. CPI this month: the efficiency of this month alone, so the best month can be found.

Sheet Results
A1: Results | D1: The Project Control Hub
A2: Every measure for the reporting month, with what it means in one line.
A3: Nothing to fill in here. It reads the Monthly row for "This report: month".
A5: THIS MONTH
A6: Planned value, PV ($) | B6: =IF(NOT(AND(Setup!$B$9<>"",ISNUMBER(INDEX(Monthly!$D$7:$D$30,Setup!$B$9)),ISNUMBER(INDEX(Monthly!$E$7:$E$30,Setup!$B$9)),ISNUMBER(INDEX(Monthly!$C$7:$C$30,Setup!$B$9)))),"",INDEX(Monthly!$C$7:$C$30,Setup!$B$9)) | D6: The promise: what the baseline said would be built by now.
A7: Earned value, EV ($) | B7: =IF(NOT(AND(Setup!$B$9<>"",ISNUMBER(INDEX(Monthly!$D$7:$D$30,Setup!$B$9)),ISNUMBER(INDEX(Monthly!$E$7:$E$30,Setup!$B$9)),ISNUMBER(INDEX(Monthly!$C$7:$C$30,Setup!$B$9)))),"",INDEX(Monthly!$D$7:$D$30,Setup!$B$9)) | D7: What is standing: the budget of the work actually done.
A8: Actual cost, AC ($) | B8: =IF(NOT(AND(Setup!$B$9<>"",ISNUMBER(INDEX(Monthly!$D$7:$D$30,Setup!$B$9)),ISNUMBER(INDEX(Monthly!$E$7:$E$30,Setup!$B$9)),ISNUMBER(INDEX(Monthly!$C$7:$C$30,Setup!$B$9)))),"",INDEX(Monthly!$E$7:$E$30,Setup!$B$9)) | D8: What has left the bank. Invoices, not opinions.
A9: Cost performance index, CPI = EV ÷ AC | B9: =IF(NOT(AND(Setup!$B$9<>"",ISNUMBER(INDEX(Monthly!$D$7:$D$30,Setup!$B$9)),ISNUMBER(INDEX(Monthly!$E$7:$E$30,Setup!$B$9)),ISNUMBER(INDEX(Monthly!$C$7:$C$30,Setup!$B$9)))),"",B7/B8) | D9: Cents of work bought with every dollar spent.
A10: Schedule performance index, SPI = EV ÷ PV | B10: =IF(NOT(AND(Setup!$B$9<>"",ISNUMBER(INDEX(Monthly!$D$7:$D$30,Setup!$B$9)),ISNUMBER(INDEX(Monthly!$E$7:$E$30,Setup!$B$9)),ISNUMBER(INDEX(Monthly!$C$7:$C$30,Setup!$B$9)))),"",B7/B6) | D10: In money. Creeps back to 1.0 at the end, even on a late job.
A11: Cost variance, CV = EV − AC ($) | B11: =IF(NOT(AND(Setup!$B$9<>"",ISNUMBER(INDEX(Monthly!$D$7:$D$30,Setup!$B$9)),ISNUMBER(INDEX(Monthly!$E$7:$E$30,Setup!$B$9)),ISNUMBER(INDEX(Monthly!$C$7:$C$30,Setup!$B$9)))),"",B7-B8) | D11: Negative: the work cost more than it was worth.
A12: Schedule variance, SV = EV − PV ($) | B12: =IF(NOT(AND(Setup!$B$9<>"",ISNUMBER(INDEX(Monthly!$D$7:$D$30,Setup!$B$9)),ISNUMBER(INDEX(Monthly!$E$7:$E$30,Setup!$B$9)),ISNUMBER(INDEX(Monthly!$C$7:$C$30,Setup!$B$9)))),"",B7-B6) | D12: Negative: less built than promised, measured in money.
A13: AT COMPLETION
A14: Budget at completion, BAC ($) | B14: =Setup!B7 | D14: From Setup.
A15: Estimate at completion, EAC = BAC ÷ CPI ($) | B15: =IF(NOT(AND(Setup!$B$9<>"",ISNUMBER(INDEX(Monthly!$D$7:$D$30,Setup!$B$9)),ISNUMBER(INDEX(Monthly!$E$7:$E$30,Setup!$B$9)),ISNUMBER(INDEX(Monthly!$C$7:$C$30,Setup!$B$9)))),"",IF(B9=0,"",B14/B9)) | D15: Where this ends if nothing changes.
A16: Variance at completion, VAC = BAC − EAC ($) | B16: =IF(NOT(AND(Setup!$B$9<>"",ISNUMBER(INDEX(Monthly!$D$7:$D$30,Setup!$B$9)),ISNUMBER(INDEX(Monthly!$E$7:$E$30,Setup!$B$9)),ISNUMBER(INDEX(Monthly!$C$7:$C$30,Setup!$B$9)))),"",IF(B15="","",B14-B15)) | D16: Negative: the overrun somebody has to find.
A17: Estimate to complete, ETC = EAC − AC ($) | B17: =IF(NOT(AND(Setup!$B$9<>"",ISNUMBER(INDEX(Monthly!$D$7:$D$30,Setup!$B$9)),ISNUMBER(INDEX(Monthly!$E$7:$E$30,Setup!$B$9)),ISNUMBER(INDEX(Monthly!$C$7:$C$30,Setup!$B$9)))),"",IF(B15="","",B15-B8)) | D17: Still to be paid out. A cash-flow number.
A18: To-complete index, TCPI = (BAC − EV) ÷ (BAC − AC) | B18: =IF(NOT(AND(Setup!$B$9<>"",ISNUMBER(INDEX(Monthly!$D$7:$D$30,Setup!$B$9)),ISNUMBER(INDEX(Monthly!$E$7:$E$30,Setup!$B$9)),ISNUMBER(INDEX(Monthly!$C$7:$C$30,Setup!$B$9)))),"",IF(B14=B8,"",(B14-B7)/(B14-B8))) | D18: The efficiency needed from tomorrow to still hit the budget.
A19: Improvement needed over the CPI achieved | B19: =IF(NOT(AND(Setup!$B$9<>"",ISNUMBER(INDEX(Monthly!$D$7:$D$30,Setup!$B$9)),ISNUMBER(INDEX(Monthly!$E$7:$E$30,Setup!$B$9)),ISNUMBER(INDEX(Monthly!$C$7:$C$30,Setup!$B$9)))),"",IF(OR(B18="",B9=""),"",B18/B9-1)) | D19: How much better than the proven rate the rest of the job must be.
A20: Best single month so far (CPI this month) | B20: =IF(Setup!$B$9="","",MAX(OFFSET(Monthly!$M$7,0,0,Setup!$B$9,1))) | D20: The best the site has actually done.
A21: Verdict | B21: =IF(NOT(AND(Setup!$B$9<>"",ISNUMBER(INDEX(Monthly!$D$7:$D$30,Setup!$B$9)),ISNUMBER(INDEX(Monthly!$E$7:$E$30,Setup!$B$9)),ISNUMBER(INDEX(Monthly!$C$7:$C$30,Setup!$B$9)))),"",IF(B18>B20,"TCPI beats the best month ever: a hope, not a recovery plan.",IF(B18>1,"Recovery needs better than budget performance. Test it.","The budget is still within reach.")))
A22: IN MONTHS, NOT MONEY
A23: Earned schedule, ES (months) | B23: =IF(NOT(AND(Setup!$B$9<>"",ISNUMBER(INDEX(Monthly!$D$7:$D$30,Setup!$B$9)),ISNUMBER(INDEX(Monthly!$E$7:$E$30,Setup!$B$9)),ISNUMBER(INDEX(Monthly!$C$7:$C$30,Setup!$B$9)))),"",INDEX(Monthly!$J$7:$J$30,Setup!$B$9)) | D23: The month the plan said you would reach today’s EV.
A24: Actual time, AT (months) | B24: =Setup!B9 | D24: The reporting month.
A25: Schedule performance in time, SPI(t) = ES ÷ AT | B25: =IF(NOT(AND(Setup!$B$9<>"",ISNUMBER(INDEX(Monthly!$D$7:$D$30,Setup!$B$9)),ISNUMBER(INDEX(Monthly!$E$7:$E$30,Setup!$B$9)),ISNUMBER(INDEX(Monthly!$C$7:$C$30,Setup!$B$9)))),"",IF(B24=0,"",B23/B24)) | D25: Unlike SPI, it does not drift back to 1.0.
A26: Delay to date (months) = AT − ES | B26: =IF(NOT(AND(Setup!$B$9<>"",ISNUMBER(INDEX(Monthly!$D$7:$D$30,Setup!$B$9)),ISNUMBER(INDEX(Monthly!$E$7:$E$30,Setup!$B$9)),ISNUMBER(INDEX(Monthly!$C$7:$C$30,Setup!$B$9)))),"",B24-B23) | D26: One number a site manager understands.
A27: Forecast duration at this pace (months) | B27: =IF(NOT(AND(Setup!$B$9<>"",ISNUMBER(INDEX(Monthly!$D$7:$D$30,Setup!$B$9)),ISNUMBER(INDEX(Monthly!$E$7:$E$30,Setup!$B$9)),ISNUMBER(INDEX(Monthly!$C$7:$C$30,Setup!$B$9)))),"",IF(OR(B25="",B25=0,Setup!B8=""),"",Setup!B8/B25)) | D27: Planned duration ÷ SPI(t). A trend, not a promise.
A28: Forecast finish | B28: =IF(NOT(AND(Setup!$B$9<>"",ISNUMBER(INDEX(Monthly!$D$7:$D$30,Setup!$B$9)),ISNUMBER(INDEX(Monthly!$E$7:$E$30,Setup!$B$9)),ISNUMBER(INDEX(Monthly!$C$7:$C$30,Setup!$B$9)))),"",IF(OR(B27="",Setup!B10=""),"",EOMONTH(Setup!B10,ROUNDUP(B27,0)-1))) | D28: The month that pace lands in.
A31: FOUR WAYS TO FORECAST THE FINISH COST
A32: Method | B32: EAC ($) | D32: When it fits
A33: 1 · BAC ÷ CPI | B33: =IF(NOT(AND(Setup!$B$9<>"",ISNUMBER(INDEX(Monthly!$D$7:$D$30,Setup!$B$9)),ISNUMBER(INDEX(Monthly!$E$7:$E$30,Setup!$B$9)),ISNUMBER(INDEX(Monthly!$C$7:$C$30,Setup!$B$9)))),"",B15) | D33: Performance so far continues. The default, and the one in the lessons.
A34: 2 · AC + (BAC − EV) | B34: =IF(NOT(AND(Setup!$B$9<>"",ISNUMBER(INDEX(Monthly!$D$7:$D$30,Setup!$B$9)),ISNUMBER(INDEX(Monthly!$E$7:$E$30,Setup!$B$9)),ISNUMBER(INDEX(Monthly!$C$7:$C$30,Setup!$B$9)))),"",B8+(B14-B7)) | D34: The overrun was a one-off and the rest goes to budget. Prove it before you use it.
A35: 3 · AC + (BAC − EV) ÷ (CPI × SPI) | B35: =IF(NOT(AND(Setup!$B$9<>"",ISNUMBER(INDEX(Monthly!$D$7:$D$30,Setup!$B$9)),ISNUMBER(INDEX(Monthly!$E$7:$E$30,Setup!$B$9)),ISNUMBER(INDEX(Monthly!$C$7:$C$30,Setup!$B$9)))),"",IF(B9*B10=0,"",B8+(B14-B7)/(B9*B10))) | D35: Cost and schedule both drag: lateness costs money. Usually the most pessimistic.
A36: 4 · AC + a bottom-up estimate of what is left | B36: =IF(OR(B8="",B37=""),"",B8+B37) | D36: Re-estimate the remaining work from scratch. Type it below.
A37: Bottom-up estimate of the remaining work ($) | D37: Optional. Leave empty if you have not re-estimated.
A40: IN PLAIN ENGLISH
A41: =IF(NOT(AND(Setup!$B$9<>"",ISNUMBER(INDEX(Monthly!$D$7:$D$30,Setup!$B$9)),ISNUMBER(INDEX(Monthly!$E$7:$E$30,Setup!$B$9)),ISNUMBER(INDEX(Monthly!$C$7:$C$30,Setup!$B$9)))),"","Every dollar spent so far bought "&TEXT(B9*100,"0")&" cents of work. If nothing changes, the job finishes at "&TEXT(B15,"$#,##0")&", "&TEXT(-B16,"$#,##0")&" over budget, with "&TEXT(B17,"$#,##0")&" still to pay. To hit the budget, every remaining dollar must buy "&TEXT(B18,"0.00")&" of work; the best month so far bought "&TEXT(B20,"0.00")&". The job is "&TEXT(B26,"0.0")&" month(s) behind: "&TEXT(B23,"0.0")&" months of plan earned in "&B24&" months of calendar.")
A45: If the tender sum is your BAC, the CPI is flattered: overhead, profit and reserve sit inside it. Build the forecast on the budget you control.

Sheet Work packages
A1: Work packages | N1: The Project Control Hub
A2: Where the money is being lost: EV and AC for each package, measured by a rule decided in advance.
A3: Pick the measuring rule before the work starts, never after. Units complete wherever there is something to count.
A6: Work package | B6: Budget ($) | C6: How EV is measured | D6: Planned % to date | E6: Measured % complete | F6: PV ($) | G6: EV ($) | H6: AC ($) | I6: CV ($) | J6: SV ($) | K6: CPI | L6: SPI | M6: Flag | N6: The rule, in words
F7: =IF(OR(B7="",D7=""),"",B7*D7) | G7: =IF(OR(B7="",E7=""),"",B7*E7) | I7: =IF(OR(G7="",H7=""),"",G7-H7) | J7: =IF(OR(G7="",F7=""),"",G7-F7) | K7: =IF(OR(G7="",H7="",H7=0),"",G7/H7) | L7: =IF(OR(G7="",F7="",F7=0),"",G7/F7) | M7: =IF(A7="","",IF(AND(K7<>"",K7<0.9),"Losing money",IF(AND(L7<>"",L7<0.9),"Behind",IF(AND(K7="",H7>0),"Cost, no progress","—"))))
F8: =IF(OR(B8="",D8=""),"",B8*D8) | G8: =IF(OR(B8="",E8=""),"",B8*E8) | I8: =IF(OR(G8="",H8=""),"",G8-H8) | J8: =IF(OR(G8="",F8=""),"",G8-F8) | K8: =IF(OR(G8="",H8="",H8=0),"",G8/H8) | L8: =IF(OR(G8="",F8="",F8=0),"",G8/F8) | M8: =IF(A8="","",IF(AND(K8<>"",K8<0.9),"Losing money",IF(AND(L8<>"",L8<0.9),"Behind",IF(AND(K8="",H8>0),"Cost, no progress","—"))))
F9: =IF(OR(B9="",D9=""),"",B9*D9) | G9: =IF(OR(B9="",E9=""),"",B9*E9) | I9: =IF(OR(G9="",H9=""),"",G9-H9) | J9: =IF(OR(G9="",F9=""),"",G9-F9) | K9: =IF(OR(G9="",H9="",H9=0),"",G9/H9) | L9: =IF(OR(G9="",F9="",F9=0),"",G9/F9) | M9: =IF(A9="","",IF(AND(K9<>"",K9<0.9),"Losing money",IF(AND(L9<>"",L9<0.9),"Behind",IF(AND(K9="",H9>0),"Cost, no progress","—"))))
F10: =IF(OR(B10="",D10=""),"",B10*D10) | G10: =IF(OR(B10="",E10=""),"",B10*E10) | I10: =IF(OR(G10="",H10=""),"",G10-H10) | J10: =IF(OR(G10="",F10=""),"",G10-F10) | K10: =IF(OR(G10="",H10="",H10=0),"",G10/H10) | L10: =IF(OR(G10="",F10="",F10=0),"",G10/F10) | M10: =IF(A10="","",IF(AND(K10<>"",K10<0.9),"Losing money",IF(AND(L10<>"",L10<0.9),"Behind",IF(AND(K10="",H10>0),"Cost, no progress","—"))))
F11: =IF(OR(B11="",D11=""),"",B11*D11) | G11: =IF(OR(B11="",E11=""),"",B11*E11) | I11: =IF(OR(G11="",H11=""),"",G11-H11) | J11: =IF(OR(G11="",F11=""),"",G11-F11) | K11: =IF(OR(G11="",H11="",H11=0),"",G11/H11) | L11: =IF(OR(G11="",F11="",F11=0),"",G11/F11) | M11: =IF(A11="","",IF(AND(K11<>"",K11<0.9),"Losing money",IF(AND(L11<>"",L11<0.9),"Behind",IF(AND(K11="",H11>0),"Cost, no progress","—"))))
F12: =IF(OR(B12="",D12=""),"",B12*D12) | G12: =IF(OR(B12="",E12=""),"",B12*E12) | I12: =IF(OR(G12="",H12=""),"",G12-H12) | J12: =IF(OR(G12="",F12=""),"",G12-F12) | K12: =IF(OR(G12="",H12="",H12=0),"",G12/H12) | L12: =IF(OR(G12="",F12="",F12=0),"",G12/F12) | M12: =IF(A12="","",IF(AND(K12<>"",K12<0.9),"Losing money",IF(AND(L12<>"",L12<0.9),"Behind",IF(AND(K12="",H12>0),"Cost, no progress","—"))))
F13: =IF(OR(B13="",D13=""),"",B13*D13) | G13: =IF(OR(B13="",E13=""),"",B13*E13) | I13: =IF(OR(G13="",H13=""),"",G13-H13) | J13: =IF(OR(G13="",F13=""),"",G13-F13) | K13: =IF(OR(G13="",H13="",H13=0),"",G13/H13) | L13: =IF(OR(G13="",F13="",F13=0),"",G13/F13) | M13: =IF(A13="","",IF(AND(K13<>"",K13<0.9),"Losing money",IF(AND(L13<>"",L13<0.9),"Behind",IF(AND(K13="",H13>0),"Cost, no progress","—"))))
F14: =IF(OR(B14="",D14=""),"",B14*D14) | G14: =IF(OR(B14="",E14=""),"",B14*E14) | I14: =IF(OR(G14="",H14=""),"",G14-H14) | J14: =IF(OR(G14="",F14=""),"",G14-F14) | K14: =IF(OR(G14="",H14="",H14=0),"",G14/H14) | L14: =IF(OR(G14="",F14="",F14=0),"",G14/F14) | M14: =IF(A14="","",IF(AND(K14<>"",K14<0.9),"Losing money",IF(AND(L14<>"",L14<0.9),"Behind",IF(AND(K14="",H14>0),"Cost, no progress","—"))))
F15: =IF(OR(B15="",D15=""),"",B15*D15) | G15: =IF(OR(B15="",E15=""),"",B15*E15) | I15: =IF(OR(G15="",H15=""),"",G15-H15) | J15: =IF(OR(G15="",F15=""),"",G15-F15) | K15: =IF(OR(G15="",H15="",H15=0),"",G15/H15) | L15: =IF(OR(G15="",F15="",F15=0),"",G15/F15) | M15: =IF(A15="","",IF(AND(K15<>"",K15<0.9),"Losing money",IF(AND(L15<>"",L15<0.9),"Behind",IF(AND(K15="",H15>0),"Cost, no progress","—"))))
F16: =IF(OR(B16="",D16=""),"",B16*D16) | G16: =IF(OR(B16="",E16=""),"",B16*E16) | I16: =IF(OR(G16="",H16=""),"",G16-H16) | J16: =IF(OR(G16="",F16=""),"",G16-F16) | K16: =IF(OR(G16="",H16="",H16=0),"",G16/H16) | L16: =IF(OR(G16="",F16="",F16=0),"",G16/F16) | M16: =IF(A16="","",IF(AND(K16<>"",K16<0.9),"Losing money",IF(AND(L16<>"",L16<0.9),"Behind",IF(AND(K16="",H16>0),"Cost, no progress","—"))))
F17: =IF(OR(B17="",D17=""),"",B17*D17) | G17: =IF(OR(B17="",E17=""),"",B17*E17) | I17: =IF(OR(G17="",H17=""),"",G17-H17) | J17: =IF(OR(G17="",F17=""),"",G17-F17) | K17: =IF(OR(G17="",H17="",H17=0),"",G17/H17) | L17: =IF(OR(G17="",F17="",F17=0),"",G17/F17) | M17: =IF(A17="","",IF(AND(K17<>"",K17<0.9),"Losing money",IF(AND(L17<>"",L17<0.9),"Behind",IF(AND(K17="",H17>0),"Cost, no progress","—"))))
F18: =IF(OR(B18="",D18=""),"",B18*D18) | G18: =IF(OR(B18="",E18=""),"",B18*E18) | I18: =IF(OR(G18="",H18=""),"",G18-H18) | J18: =IF(OR(G18="",F18=""),"",G18-F18) | K18: =IF(OR(G18="",H18="",H18=0),"",G18/H18) | L18: =IF(OR(G18="",F18="",F18=0),"",G18/F18) | M18: =IF(A18="","",IF(AND(K18<>"",K18<0.9),"Losing money",IF(AND(L18<>"",L18<0.9),"Behind",IF(AND(K18="",H18>0),"Cost, no progress","—"))))
... F26: =IF(OR(B26="",D26=""),"",B26*D26) | G26: =IF(OR(B26="",E26=""),"",B26*E26) | I26: =IF(OR(G26="",H26=""),"",G26-H26) | J26: =IF(OR(G26="",F26=""),"",G26-F26) | K26: =IF(OR(G26="",H26="",H26=0),"",G26/H26) | L26: =IF(OR(G26="",F26="",F26=0),"",G26/F26) | M26: =IF(A26="","",IF(AND(K26<>"",K26<0.9),"Losing money",IF(AND(L26<>"",L26<0.9),"Behind",IF(AND(K26="",H26>0),"Cost, no progress","—"))))
A28: Total | B28: =SUM(B7:B26) | F28: =SUM(F7:F26) | G28: =SUM(G7:G26) | H28: =SUM(H7:H26) | I28: =SUM(I7:I26) | J28: =SUM(J7:J26) | K28: =IF(H28=0,"",G28/H28) | L28: =IF(F28=0,"",G28/F28)
A29: Check against the Monthly sheet | B29: =IF(Setup!B7="","",IF(ROUND(B28-Setup!B7,0)=0,"✔ BAC matches","BAC differs")) | G29: =IF(Results!B7="","",IF(ROUND(G28-Results!B7,0)=0,"✔ EV matches","EV differs by "&TEXT(G28-Results!B7,"$#,##0"))) | H29: =IF(Results!B8="","",IF(ROUND(H28-Results!B8,0)=0,"✔ AC matches","AC differs by "&TEXT(H28-Results!B8,"$#,##0")))
A31: MEASURING RULES
A32: Units complete | B32: Count something: piles, metres, tonnes. The most honest rule wherever there is something to count.
A33: Milestones | B33: Fixed weights for fixed steps, agreed in advance. Good for equipment and long single items.
A34: 0/100 | B34: Nothing until it is finished. For short tasks, under one reporting period.
A35: 50/50 | B35: Half when it starts, half when it finishes. For tasks spanning two periods.
A36: Level of effort | B36: Earns with the calendar. Use only for support work; it hides progress problems.
